<annotation>
	<folder>train</folder>
	<filename>1389_1.jpg</filename>
	<path>C:\Users\salam\Documents\Image_for_training\train\1389_1.jpg</path>
	<source>
		<database>Unknown</database>
	</source>
	<size>
		<width>500</width>
		<height>317</height>
		<depth>3</depth>
	</size>
	<segmented>0</segmented>
	<object>
		<name>car</name>
		<pose>Unspecified</pose>
		<truncated>0</truncated>
		<difficult>0</difficult>
		<bndbox>
			<xmin>71</xmin>
			<ymin>100</ymin>
			<xmax>420</xmax>
			<ymax>295</ymax>
		</bndbox>
	</object>
	<object>
		<name>car</name>
		<pose>Unspecified</pose>
		<truncated>0</truncated>
		<difficult>0</difficult>
		<bndbox>
			<xmin>415</xmin>
			<ymin>207</ymin>
			<xmax>476</xmax>
			<ymax>257</ymax>
		</bndbox>
	</object>
</annotation>