<annotation>
	<folder>train</folder>
	<filename>1492_1.jpg</filename>
	<path>C:\Users\salam\Documents\Image_for_training\train\1492_1.jpg</path>
	<source>
		<database>Unknown</database>
	</source>
	<size>
		<width>400</width>
		<height>280</height>
		<depth>3</depth>
	</size>
	<segmented>0</segmented>
	<object>
		<name>car</name>
		<pose>Unspecified</pose>
		<truncated>0</truncated>
		<difficult>0</difficult>
		<bndbox>
			<xmin>23</xmin>
			<ymin>127</ymin>
			<xmax>362</xmax>
			<ymax>262</ymax>
		</bndbox>
	</object>
	<object>
		<name>targa</name>
		<pose>Unspecified</pose>
		<truncated>0</truncated>
		<difficult>0</difficult>
		<bndbox>
			<xmin>76</xmin>
			<ymin>212</ymin>
			<xmax>118</xmax>
			<ymax>228</ymax>
		</bndbox>
	</object>
</annotation>