<annotation>
	<folder>train</folder>
	<filename>1526_1.jpg</filename>
	<path>C:\Users\salam\Documents\Image_for_training\train\1526_1.jpg</path>
	<source>
		<database>Unknown</database>
	</source>
	<size>
		<width>480</width>
		<height>360</height>
		<depth>3</depth>
	</size>
	<segmented>0</segmented>
	<object>
		<name>car</name>
		<pose>Unspecified</pose>
		<truncated>0</truncated>
		<difficult>0</difficult>
		<bndbox>
			<xmin>31</xmin>
			<ymin>153</ymin>
			<xmax>444</xmax>
			<ymax>343</ymax>
		</bndbox>
	</object>
	<object>
		<name>person</name>
		<pose>Unspecified</pose>
		<truncated>0</truncated>
		<difficult>0</difficult>
		<bndbox>
			<xmin>105</xmin>
			<ymin>147</ymin>
			<xmax>121</xmax>
			<ymax>187</ymax>
		</bndbox>
	</object>
	<object>
		<name>car</name>
		<pose>Unspecified</pose>
		<truncated>0</truncated>
		<difficult>0</difficult>
		<bndbox>
			<xmin>45</xmin>
			<ymin>147</ymin>
			<xmax>102</xmax>
			<ymax>186</ymax>
		</bndbox>
	</object>
</annotation>