<annotation>
    <folder>train</folder>
    <filename>2239.jpg</filename>
    <path>C:\Users\salam\Documents\Image_for_training\train\2239.jpg</path>
    <source>
        <database>Unknown</database>
    </source>
    <size>
        <width>800</width>
        <height>600</height>
        <depth>3</depth>
    </size>
    <segmented>0</segmented>
    <object>
        <name>car</name>
        <pose>Unspecified</pose>
        <truncated>0</truncated>
        <difficult>0</difficult>
        <bndbox>
            <xmin>48</xmin>
            <ymin>169</ymin>
            <xmax>710</xmax>
            <ymax>551</ymax>
        </bndbox>
    </object>
</annotation>
