<annotation>
	<folder>train</folder>
	<filename>2363.jpg</filename>
	<path>C:\Users\salam\Documents\Image_for_training\train\2363.jpg</path>
	<source>
		<database>Unknown</database>
	</source>
	<size>
		<width>1280</width>
		<height>949</height>
		<depth>3</depth>
	</size>
	<segmented>0</segmented>
	<object>
		<name>car</name>
		<pose>Unspecified</pose>
		<truncated>0</truncated>
		<difficult>0</difficult>
		<bndbox>
			<xmin>185</xmin>
			<ymin>186</ymin>
			<xmax>937</xmax>
			<ymax>813</ymax>
		</bndbox>
	</object>
	<object>
		<name>targa</name>
		<pose>Unspecified</pose>
		<truncated>0</truncated>
		<difficult>0</difficult>
		<bndbox>
			<xmin>355</xmin>
			<ymin>519</ymin>
			<xmax>578</xmax>
			<ymax>583</ymax>
		</bndbox>
	</object>
</annotation>
