<annotation>
	<folder>train</folder>
	<filename>5005.jpg</filename>
	<path>C:\Users\salam\Documents\Image_for_training\train\5005.jpg</path>
	<source>
		<database>Unknown</database>
	</source>
	<size>
		<width>500</width>
		<height>375</height>
		<depth>3</depth>
	</size>
	<segmented>0</segmented>
	<object>
		<name>car</name>
		<pose>Unspecified</pose>
		<truncated>0</truncated>
		<difficult>0</difficult>
		<bndbox>
			<xmin>33</xmin>
			<ymin>152</ymin>
			<xmax>486</xmax>
			<ymax>301</ymax>
		</bndbox>
	</object>
	<object>
		<name>car</name>
		<pose>Unspecified</pose>
		<truncated>0</truncated>
		<difficult>0</difficult>
		<bndbox>
			<xmin>220</xmin>
			<ymin>118</ymin>
			<xmax>449</xmax>
			<ymax>195</ymax>
		</bndbox>
	</object>
</annotation>
