<annotation>
    <folder>train</folder>
    <filename>5673.jpg</filename>
    <path>C:\Users\salam\Documents\Image_for_training\train\5673.jpg</path>
    <source>
        <database>Unknown</database>
    </source>
    <size>
        <width>800</width>
        <height>600</height>
        <depth>3</depth>
    </size>
    <segmented>0</segmented>
    <object>
        <name>car</name>
        <pose>Unspecified</pose>
        <truncated>0</truncated>
        <difficult>0</difficult>
        <bndbox>
            <xmin>97</xmin>
            <ymin>182</ymin>
            <xmax>700</xmax>
            <ymax>530</ymax>
        </bndbox>
    </object>    <object>
        <name>car</name>
        <pose>Unspecified</pose>
        <truncated>0</truncated>
        <difficult>0</difficult>
        <bndbox>
            <xmin>642</xmin>
            <ymin>199</ymin>
            <xmax>767</xmax>
            <ymax>259</ymax>
        </bndbox>
    </object>    <object>
        <name>car</name>
        <pose>Unspecified</pose>
        <truncated>0</truncated>
        <difficult>0</difficult>
        <bndbox>
            <xmin>186</xmin>
            <ymin>184</ymin>
            <xmax>370</xmax>
            <ymax>281</ymax>
        </bndbox>
    </object>    <object>
        <name>car</name>
        <pose>Unspecified</pose>
        <truncated>0</truncated>
        <difficult>0</difficult>
        <bndbox>
            <xmin>681</xmin>
            <ymin>202</ymin>
            <xmax>782</xmax>
            <ymax>257</ymax>
        </bndbox>
    </object>    <object>
        <name>car</name>
        <pose>Unspecified</pose>
        <truncated>0</truncated>
        <difficult>0</difficult>
        <bndbox>
            <xmin>70</xmin>
            <ymin>183</ymin>
            <xmax>252</xmax>
            <ymax>290</ymax>
        </bndbox>
    </object>
</annotation>
