<annotation>
    <folder>train</folder>
    <filename>6046.jpg</filename>
    <path>C:\Users\salam\Documents\Image_for_training\train\6046.jpg</path>
    <source>
        <database>Unknown</database>
    </source>
    <size>
        <width>550</width>
        <height>400</height>
        <depth>3</depth>
    </size>
    <segmented>0</segmented>
    <object>
        <name>car</name>
        <pose>Unspecified</pose>
        <truncated>0</truncated>
        <difficult>0</difficult>
        <bndbox>
            <xmin>56</xmin>
            <ymin>117</ymin>
            <xmax>517</xmax>
            <ymax>367</ymax>
        </bndbox>
    </object>
</annotation>
