<annotation>
    <folder>train</folder>
    <filename>6158.jpg</filename>
    <path>C:\Users\salam\Documents\Image_for_training\train\6158.jpg</path>
    <source>
        <database>Unknown</database>
    </source>
    <size>
        <width>300</width>
        <height>165</height>
        <depth>3</depth>
    </size>
    <segmented>0</segmented>
    <object>
        <name>car</name>
        <pose>Unspecified</pose>
        <truncated>0</truncated>
        <difficult>0</difficult>
        <bndbox>
            <xmin>33</xmin>
            <ymin>35</ymin>
            <xmax>257</xmax>
            <ymax>136</ymax>
        </bndbox>
    </object>
</annotation>
