<annotation>
    <folder>train</folder>
    <filename>629_1.jpg</filename>
    <path>C:\Users\salam\Documents\Image_for_training\train\629_1.jpg</path>
    <source>
        <database>Unknown</database>
    </source>
    <size>
        <width>595</width>
        <height>445</height>
        <depth>3</depth>
    </size>
    <segmented>0</segmented>
    <object>
        <name>car</name>
        <pose>Unspecified</pose>
        <truncated>0</truncated>
        <difficult>0</difficult>
        <bndbox>
            <xmin>49</xmin>
            <ymin>102</ymin>
            <xmax>548</xmax>
            <ymax>438</ymax>
        </bndbox>
    </object>
</annotation>