<annotation>
	<folder>train</folder>
	<filename>634_1.jpg</filename>
	<path>C:\Users\salam\Documents\Image_for_training\train\634_1.jpg</path>
	<source>
		<database>Unknown</database>
	</source>
	<size>
		<width>1280</width>
		<height>960</height>
		<depth>3</depth>
	</size>
	<segmented>0</segmented>
	<object>
		<name>car</name>
		<pose>Unspecified</pose>
		<truncated>0</truncated>
		<difficult>0</difficult>
		<bndbox>
			<xmin>235</xmin>
			<ymin>157</ymin>
			<xmax>1128</xmax>
			<ymax>831</ymax>
		</bndbox>
	</object>
	<object>
		<name>car</name>
		<pose>Unspecified</pose>
		<truncated>0</truncated>
		<difficult>0</difficult>
		<bndbox>
			<xmin>3</xmin>
			<ymin>236</ymin>
			<xmax>199</xmax>
			<ymax>367</ymax>
		</bndbox>
	</object>
	<object>
		<name>car</name>
		<pose>Unspecified</pose>
		<truncated>0</truncated>
		<difficult>0</difficult>
		<bndbox>
			<xmin>206</xmin>
			<ymin>235</ymin>
			<xmax>402</xmax>
			<ymax>366</ymax>
		</bndbox>
	</object>
</annotation>